[{"step": 22, "collisions": [{"kind": "begin", "1": {"id": 13, "type": "circle", "x": 30.4221, "y": 27.089, "x_vel": 0, "y_vel": 0, "angle": 0, "color": "Black"}, "2": {"id": 43, "type": "User Circle", "x": 29.1667, "y": 31.1446, "x_vel": 0, "y_vel": -3.59333, "angle": 0, "color": "Red"}}, {"kind": "begin", "1": {"id": 6, "type": "circle", "x": 30.4221, "y": 27.089, "x_vel": 0, "y_vel": 0, "angle": 0, "color": "Black"}, "2": {"id": 43, "type": "User Circle", "x": 29.1667, "y": 31.1446, "x_vel": 0, "y_vel": -3.59333, "angle": 0, "color": "Red"}}], "list": [{"id": 43, "type": "User Circle", "x": 29.1513, "y": 31.1524, "x_vel": -0.919387, "y_vel": 0.466727, "angle": 0.00389885, "color": "Red"}, {"id": 4, "type": "circle", "x": 24.7328, "y": 37.6487, "x_vel": 0, "y_vel": -3.75667, "angle": 0, "color": "Green"}], "solved_state": false}, {"step": 23, "collisions": [{"kind": "end", "1": {"id": 13, "type": "circle", "x": 30.4221, "y": 27.089, "x_vel": 0, "y_vel": 0, "angle": 0, "color": "Black"}, "2": {"id": 43, "type": "User Circle", "x": 29.1513, "y": 31.1524, "x_vel": -0.919387, "y_vel": 0.466727, "angle": 0.00389885, "color": "Red"}}, {"kind": "end", "1": {"id": 6, "type": "circle", "x": 30.4221, "y": 27.089, "x_vel": 0, "y_vel": 0, "angle": 0, "color": "Black"}, "2": {"id": 43, "type": "User Circle", "x": 29.1513, "y": 31.1524, "x_vel": -0.919387, "y_vel": 0.466727, "angle": 0.00389885, "color": "Red"}}], "list": [{"id": 43, "type": "User Circle", "x": 29.136, "y": 31.1574, "x_vel": -0.919387, "y_vel": 0.303394, "angle": 0.00779704, "color": "Red"}, {"id": 4, "type": "circle", "x": 24.7328, "y": 37.5833, "x_vel": 0, "y_vel": -3.92, "angle": 0, "color": "Green"}], "solved_state": false}, {"step": 33, "collisions": [{"kind": "begin", "1": {"id": 13, "type": "circle", "x": 30.4221, "y": 27.089, "x_vel": 0, "y_vel": 0, "angle": 0, "color": "Black"}, "2": {"id": 43, "type": "User Circle", "x": 28.9981, "y": 31.0805, "x_vel": -0.919387, "y_vel": -1.16661, "angle": 0.0428516, "color": "Red"}}, {"kind": "begin", "1": {"id": 6, "type": "circle", "x": 30.4221, "y": 27.089, "x_vel": 0, "y_vel": 0, "angle": 0, "color": "Black"}, "2": {"id": 43, "type": "User Circle", "x": 28.9981, "y": 31.0805, "x_vel": -0.919387, "y_vel": -1.16661, "angle": 0.0428516, "color": "Red"}}], "list": [{"id": 43, "type": "User Circle", "x": 28.9796, "y": 31.0766, "x_vel": -1.05556, "y_vel": -0.376588, "angle": 0.0487615, "color": "Red"}, {"id": 4, "type": "circle", "x": 24.7328, "y": 36.7803, "x_vel": 0, "y_vel": -5.55333, "angle": 0, "color": "Green"}], "solved_state": false}, {"step": 53, "collisions": [{"kind": "begin", "1": {"id": 4, "type": "circle", "x": 24.7328, "y": 34.5045, "x_vel": 0, "y_vel": -8.65667, "angle": 0, "color": "Green"}, "2": {"id": 43, "type": "User Circle", "x": 28.5347, "y": 30.8925, "x_vel": -1.723, "y_vel": -0.838945, "angle": 0.201091, "color": "Red"}}], "list": [{"id": 43, "type": "User Circle", "x": 28.5087, "y": 30.8796, "x_vel": -1.55665, "y_vel": -0.772487, "angle": 0.210243, "color": "Red"}, {"id": 4, "type": "circle", "x": 24.6478, "y": 34.4615, "x_vel": -5.10272, "y_vel": -2.57864, "angle": 0.0161397, "color": "Green"}], "solved_state": false}, {"step": 54, "collisions": [{"kind": "end", "1": {"id": 4, "type": "circle", "x": 24.6478, "y": 34.4615, "x_vel": -5.10272, "y_vel": -2.57864, "angle": 0.0161397, "color": "Green"}, "2": {"id": 43, "type": "User Circle", "x": 28.5087, "y": 30.8796, "x_vel": -1.55665, "y_vel": -0.772487, "angle": 0.210243, "color": "Red"}}], "list": [{"id": 43, "type": "User Circle", "x": 28.4821, "y": 30.8662, "x_vel": -1.59503, "y_vel": -0.805137, "angle": 0.219653, "color": "Red"}, {"id": 4, "type": "circle", "x": 24.5627, "y": 34.4158, "x_vel": -5.10272, "y_vel": -2.74197, "angle": 0.0322767, "color": "Green"}], "solved_state": false}, {"step": 55, "collisions": [{"kind": "begin", "1": {"id": 17, "type": "circle", "x": 25.6094, "y": 27.7526, "x_vel": 0, "y_vel": 0, "angle": 0, "color": "Black"}, "2": {"id": 43, "type": "User Circle", "x": 28.4821, "y": 30.8662, "x_vel": -1.59503, "y_vel": -0.805137, "angle": 0.219653, "color": "Red"}}, {"kind": "begin", "1": {"id": 8, "type": "circle", "x": 25.6094, "y": 27.7526, "x_vel": 0, "y_vel": 0, "angle": 0, "color": "Black"}, "2": {"id": 43, "type": "User Circle", "x": 28.4821, "y": 30.8662, "x_vel": -1.59503, "y_vel": -0.805137, "angle": 0.219653, "color": "Red"}}, {"kind": "begin", "1": {"id": 7, "type": "circle", "x": 25.6094, "y": 27.7526, "x_vel": 0, "y_vel": 0, "angle": 0, "color": "Black"}, "2": {"id": 43, "type": "User Circle", "x": 28.4821, "y": 30.8662, "x_vel": -1.59503, "y_vel": -0.805137, "angle": 0.219653, "color": "Red"}}], "list": [{"id": 43, "type": "User Circle", "x": 28.4755, "y": 30.8821, "x_vel": -0.447256, "y_vel": 0.900681, "angle": 0.224608, "color": "Red"}, {"id": 4, "type": "circle", "x": 24.4777, "y": 34.3674, "x_vel": -5.10272, "y_vel": -2.90531, "angle": 0.0484111, "color": "Green"}], "solved_state": false}, {"step": 56, "collisions": [{"kind": "end", "1": {"id": 13, "type": "circle", "x": 30.4221, "y": 27.089, "x_vel": 0, "y_vel": 0, "angle": 0, "color": "Black"}, "2": {"id": 43, "type": "User Circle", "x": 28.4755, "y": 30.8821, "x_vel": -0.447256, "y_vel": 0.900681, "angle": 0.224608, "color": "Red"}}, {"kind": "end", "1": {"id": 6, "type": "circle", "x": 30.4221, "y": 27.089, "x_vel": 0, "y_vel": 0, "angle": 0, "color": "Black"}, "2": {"id": 43, "type": "User Circle", "x": 28.4755, "y": 30.8821, "x_vel": -0.447256, "y_vel": 0.900681, "angle": 0.224608, "color": "Red"}}], "list": [{"id": 43, "type": "User Circle", "x": 28.4681, "y": 30.8944, "x_vel": -0.447256, "y_vel": 0.737348, "angle": 0.229562, "color": "Red"}, {"id": 4, "type": "circle", "x": 24.3927, "y": 34.3163, "x_vel": -5.10272, "y_vel": -3.06864, "angle": 0.0645427, "color": "Green"}], "solved_state": false}, {"step": 81, "collisions": [{"kind": "end", "1": {"id": 17, "type": "circle", "x": 25.6094, "y": 27.7526, "x_vel": 0, "y_vel": 0, "angle": 0, "color": "Black"}, "2": {"id": 43, "type": "User Circle", "x": 28.4866, "y": 30.8806, "x_vel": 0.645136, "y_vel": -0.589325, "angle": 0.228651, "color": "Red"}}, {"kind": "end", "1": {"id": 8, "type": "circle", "x": 25.6094, "y": 27.7526, "x_vel": 0, "y_vel": 0, "angle": 0, "color": "Black"}, "2": {"id": 43, "type": "User Circle", "x": 28.4866, "y": 30.8806, "x_vel": 0.645136, "y_vel": -0.589325, "angle": 0.228651, "color": "Red"}}, {"kind": "end", "1": {"id": 7, "type": "circle", "x": 25.6094, "y": 27.7526, "x_vel": 0, "y_vel": 0, "angle": 0, "color": "Black"}, "2": {"id": 43, "type": "User Circle", "x": 28.4866, "y": 30.8806, "x_vel": 0.645136, "y_vel": -0.589325, "angle": 0.228651, "color": "Red"}}], "list": [{"id": 43, "type": "User Circle", "x": 28.4973, "y": 30.8681, "x_vel": 0.645136, "y_vel": -0.752658, "angle": 0.224053, "color": "Red"}, {"id": 4, "type": "circle", "x": 22.2665, "y": 32.1529, "x_vel": -5.10272, "y_vel": -7.15198, "angle": 0.466961, "color": "Green"}], "solved_state": false}, {"step": 82, "collisions": [{"kind": "begin", "1": {"id": 13, "type": "circle", "x": 30.4221, "y": 27.089, "x_vel": 0, "y_vel": 0, "angle": 0, "color": "Black"}, "2": {"id": 43, "type": "User Circle", "x": 28.4973, "y": 30.8681, "x_vel": 0.645136, "y_vel": -0.752658, "angle": 0.224053, "color": "Red"}}, {"kind": "begin", "1": {"id": 6, "type": "circle", "x": 30.4221, "y": 27.089, "x_vel": 0, "y_vel": 0, "angle": 0, "color": "Black"}, "2": {"id": 43, "type": "User Circle", "x": 28.4973, "y": 30.8681, "x_vel": 0.645136, "y_vel": -0.752658, "angle": 0.224053, "color": "Red"}}, {"kind": "begin", "1": {"id": 17, "type": "circle", "x": 25.6094, "y": 27.7526, "x_vel": 0, "y_vel": 0, "angle": 0, "color": "Black"}, "2": {"id": 43, "type": "User Circle", "x": 28.4973, "y": 30.8681, "x_vel": 0.645136, "y_vel": -0.752658, "angle": 0.224053, "color": "Red"}}, {"kind": "begin", "1": {"id": 8, "type": "circle", "x": 25.6094, "y": 27.7526, "x_vel": 0, "y_vel": 0, "angle": 0, "color": "Black"}, "2": {"id": 43, "type": "User Circle", "x": 28.4973, "y": 30.8681, "x_vel": 0.645136, "y_vel": -0.752658, "angle": 0.224053, "color": "Red"}}, {"kind": "begin", "1": {"id": 7, "type": "circle", "x": 25.6094, "y": 27.7526, "x_vel": 0, "y_vel": 0, "angle": 0, "color": "Black"}, "2": {"id": 43, "type": "User Circle", "x": 28.4973, "y": 30.8681, "x_vel": 0.645136, "y_vel": -0.752658, "angle": 0.224053, "color": "Red"}}], "list": [{"id": 43, "type": "User Circle", "x": 28.5015, "y": 30.8745, "x_vel": 0.253358, "y_vel": 0.377958, "angle": 0.221959, "color": "Red"}, {"id": 4, "type": "circle", "x": 22.1815, "y": 32.031, "x_vel": -5.10272, "y_vel": -7.31531, "angle": 0.483023, "color": "Green"}], "solved_state": false}, {"step": 83, "collisions": [{"kind": "end", "1": {"id": 17, "type": "circle", "x": 25.6094, "y": 27.7526, "x_vel": 0, "y_vel": 0, "angle": 0, "color": "Black"}, "2": {"id": 43, "type": "User Circle", "x": 28.5015, "y": 30.8745, "x_vel": 0.253358, "y_vel": 0.377958, "angle": 0.221959, "color": "Red"}}, {"kind": "end", "1": {"id": 8, "type": "circle", "x": 25.6094, "y": 27.7526, "x_vel": 0, "y_vel": 0, "angle": 0, "color": "Black"}, "2": {"id": 43, "type": "User Circle", "x": 28.5015, "y": 30.8745, "x_vel": 0.253358, "y_vel": 0.377958, "angle": 0.221959, "color": "Red"}}, {"kind": "end", "1": {"id": 7, "type": "circle", "x": 25.6094, "y": 27.7526, "x_vel": 0, "y_vel": 0, "angle": 0, "color": "Black"}, "2": {"id": 43, "type": "User Circle", "x": 28.5015, "y": 30.8745, "x_vel": 0.253358, "y_vel": 0.377958, "angle": 0.221959, "color": "Red"}}], "list": [{"id": 43, "type": "User Circle", "x": 28.5057, "y": 30.8781, "x_vel": 0.253358, "y_vel": 0.214625, "angle": 0.219865, "color": "Red"}, {"id": 4, "type": "circle", "x": 22.0964, "y": 31.9064, "x_vel": -5.10272, "y_vel": -7.47864, "angle": 0.499083, "color": "Green"}], "solved_state": false}, {"step": 97, "collisions": [{"kind": "begin", "1": {"id": 4, "type": "circle", "x": 20.972, "y": 30.0021, "x_vel": -5.10272, "y_vel": -9.76531, "angle": 0.711169, "color": "Green"}, "2": {"id": 9, "type": "circle", "x": 20.159, "y": 26.9571, "x_vel": 0, "y_vel": 0, "angle": 0, "color": "Black"}}], "list": [{"id": 43, "type": "User Circle", "x": 28.5016, "y": 30.876, "x_vel": -0.300245, "y_vel": -0.15177, "angle": 0.221092, "color": "Red"}, {"id": 4, "type": "circle", "x": 20.9531, "y": 30.0457, "x_vel": -1.64211, "y_vel": 2.66398, "angle": 0.725336, "color": "Green"}], "solved_state": false}, {"step": 98, "collisions": [{"kind": "end", "1": {"id": 4, "type": "circle", "x": 20.9531, "y": 30.0457, "x_vel": -1.64211, "y_vel": 2.66398, "angle": 0.725336, "color": "Green"}, "2": {"id": 9, "type": "circle", "x": 20.159, "y": 26.9571, "x_vel": 0, "y_vel": 0, "angle": 0, "color": "Black"}}], "list": [{"id": 43, "type": "User Circle", "x": 28.4958, "y": 30.8731, "x_vel": -0.343935, "y_vel": -0.174425, "angle": 0.223123, "color": "Red"}, {"id": 4, "type": "circle", "x": 20.9257, "y": 30.0874, "x_vel": -1.64211, "y_vel": 2.50065, "angle": 0.743548, "color": "Green"}], "solved_state": false}, {"step": 100, "collisions": [{"kind": "begin", "1": {"id": 17, "type": "circle", "x": 25.6094, "y": 27.7526, "x_vel": 0, "y_vel": 0, "angle": 0, "color": "Black"}, "2": {"id": 43, "type": "User Circle", "x": 28.4894, "y": 30.8698, "x_vel": -0.387655, "y_vel": -0.197336, "angle": 0.225414, "color": "Red"}}, {"kind": "begin", "1": {"id": 8, "type": "circle", "x": 25.6094, "y": 27.7526, "x_vel": 0, "y_vel": 0, "angle": 0, "color": "Black"}, "2": {"id": 43, "type": "User Circle", "x": 28.4894, "y": 30.8698, "x_vel": -0.387655, "y_vel": -0.197336, "angle": 0.225414, "color": "Red"}}, {"kind": "begin", "1": {"id": 7, "type": "circle", "x": 25.6094, "y": 27.7526, "x_vel": 0, "y_vel": 0, "angle": 0, "color": "Black"}, "2": {"id": 43, "type": "User Circle", "x": 28.4894, "y": 30.8698, "x_vel": -0.387655, "y_vel": -0.197336, "angle": 0.225414, "color": "Red"}}], "list": [{"id": 43, "type": "User Circle", "x": 28.4876, "y": 30.8721, "x_vel": -0.126148, "y_vel": 0.116548, "angle": 0.226319, "color": "Red"}, {"id": 4, "type": "circle", "x": 20.871, "y": 30.1626, "x_vel": -1.64211, "y_vel": 2.17398, "angle": 0.779961, "color": "Green"}], "solved_state": false}, {"step": 102, "collisions": [{"kind": "end", "1": {"id": 13, "type": "circle", "x": 30.4221, "y": 27.089, "x_vel": 0, "y_vel": 0, "angle": 0, "color": "Black"}, "2": {"id": 43, "type": "User Circle", "x": 28.4866, "y": 30.8734, "x_vel": -0.0719857, "y_vel": 0.0664176, "angle": 0.226835, "color": "Red"}}, {"kind": "end", "1": {"id": 6, "type": "circle", "x": 30.4221, "y": 27.089, "x_vel": 0, "y_vel": 0, "angle": 0, "color": "Black"}, "2": {"id": 43, "type": "User Circle", "x": 28.4866, "y": 30.8734, "x_vel": -0.0719857, "y_vel": 0.0664176, "angle": 0.226835, "color": "Red"}}], "list": [{"id": 43, "type": "User Circle", "x": 28.4864, "y": 30.8738, "x_vel": -0.0177733, "y_vel": 0.0163859, "angle": 0.226962, "color": "Red"}, {"id": 4, "type": "circle", "x": 20.8162, "y": 30.2269, "x_vel": -1.64211, "y_vel": 1.84731, "angle": 0.816363, "color": "Green"}], "solved_state": false}, {"step": 105, "collisions": [{"kind": "begin", "1": {"id": 13, "type": "circle", "x": 30.4221, "y": 27.089, "x_vel": 0, "y_vel": 0, "angle": 0, "color": "Black"}, "2": {"id": 43, "type": "User Circle", "x": 28.4886, "y": 30.8719, "x_vel": 0.0906895, "y_vel": -0.0836269, "angle": 0.226051, "color": "Red"}}, {"kind": "begin", "1": {"id": 6, "type": "circle", "x": 30.4221, "y": 27.089, "x_vel": 0, "y_vel": 0, "angle": 0, "color": "Black"}, "2": {"id": 43, "type": "User Circle", "x": 28.4886, "y": 30.8719, "x_vel": 0.0906895, "y_vel": -0.0836269, "angle": 0.226051, "color": "Red"}}], "list": [{"id": 43, "type": "User Circle", "x": 28.4889, "y": 30.8721, "x_vel": 0.0178601, "y_vel": 0.00912871, "angle": 0.225945, "color": "Red"}, {"id": 4, "type": "circle", "x": 20.7341, "y": 30.3029, "x_vel": -1.64211, "y_vel": 1.35731, "angle": 0.870943, "color": "Green"}], "solved_state": false}, {"step": 128, "collisions": [{"kind": "begin", "1": {"id": 4, "type": "circle", "x": 20.132, "y": 30.1119, "x_vel": -1.64211, "y_vel": -2.23602, "angle": 1.27036, "color": "Green"}, "2": {"id": 9, "type": "circle", "x": 20.159, "y": 26.9571, "x_vel": 0, "y_vel": 0, "angle": 0, "color": "Black"}}], "list": [{"id": 43, "type": "User Circle", "x": 28.4889, "y": 30.8721, "x_vel": 5.10578e-16, "y_vel": -4.56432e-16, "angle": 0.225945, "color": "Red"}, {"id": 4, "type": "circle", "x": 20.1009, "y": 30.1195, "x_vel": -1.86599, "y_vel": 0.461145, "angle": 1.2853, "color": "Green"}], "solved_state": false}, {"step": 130, "collisions": [{"kind": "end", "1": {"id": 4, "type": "circle", "x": 20.0698, "y": 30.1245, "x_vel": -1.86599, "y_vel": 0.297811, "angle": 1.30024, "color": "Green"}, "2": {"id": 9, "type": "circle", "x": 20.159, "y": 26.9571, "x_vel": 0, "y_vel": 0, "angle": 0, "color": "Black"}}], "list": [{"id": 43, "type": "User Circle", "x": 28.4889, "y": 30.8721, "x_vel": -1.57144e-16, "y_vel": 1.58959e-16, "angle": 0.225945, "color": "Red"}, {"id": 4, "type": "circle", "x": 20.0387, "y": 30.1267, "x_vel": -1.86599, "y_vel": 0.134478, "angle": 1.31517, "color": "Green"}], "solved_state": false}, {"step": 135, "collisions": [{"kind": "begin", "1": {"id": 4, "type": "circle", "x": 19.9143, "y": 30.1085, "x_vel": -1.86599, "y_vel": -0.518855, "angle": 1.37488, "color": "Green"}, "2": {"id": 9, "type": "circle", "x": 20.159, "y": 26.9571, "x_vel": 0, "y_vel": 0, "angle": 0, "color": "Black"}}], "list": [{"id": 43, "type": "User Circle", "x": 28.4889, "y": 30.8721, "x_vel": 0, "y_vel": 0, "angle": 0.225945, "color": "Red"}, {"id": 4, "type": "circle", "x": 19.8828, "y": 30.1062, "x_vel": -1.89058, "y_vel": -0.14675, "angle": 1.39007, "color": "Green"}], "solved_state": false}, {"step": 163, "collisions": [{"kind": "end", "1": {"id": 4, "type": "circle", "x": 18.9394, "y": 29.8797, "x_vel": -2.36881, "y_vel": -0.951335, "angle": 1.85794, "color": "Green"}, "2": {"id": 9, "type": "circle", "x": 20.159, "y": 26.9571, "x_vel": 0, "y_vel": 0, "angle": 0, "color": "Black"}}], "list": [{"id": 43, "type": "User Circle", "x": 28.4889, "y": 30.8721, "x_vel": 0, "y_vel": 0, "angle": 0.225945, "color": "Red"}, {"id": 4, "type": "circle", "x": 18.8999, "y": 29.8611, "x_vel": -2.36881, "y_vel": -1.11467, "angle": 1.87836, "color": "Green"}], "solved_state": false}, {"step": 164, "collisions": [{"kind": "begin", "1": {"id": 4, "type": "circle", "x": 18.8999, "y": 29.8611, "x_vel": -2.36881, "y_vel": -1.11467, "angle": 1.87836, "color": "Green"}, "2": {"id": 9, "type": "circle", "x": 20.159, "y": 26.9571, "x_vel": 0, "y_vel": 0, "angle": 0, "color": "Black"}}], "list": [{"id": 43, "type": "User Circle", "x": 28.4889, "y": 30.8721, "x_vel": 0, "y_vel": 0, "angle": 0.225945, "color": "Red"}, {"id": 4, "type": "circle", "x": 18.8595, "y": 29.8436, "x_vel": -2.42042, "y_vel": -1.0494, "angle": 1.89947, "color": "Green"}], "solved_state": false}, {"step": 169, "collisions": [{"kind": "end", "1": {"id": 4, "type": "circle", "x": 18.6939, "y": 29.7647, "x_vel": -2.52303, "y_vel": -1.26921, "angle": 1.98757, "color": "Green"}, "2": {"id": 9, "type": "circle", "x": 20.159, "y": 26.9571, "x_vel": 0, "y_vel": 0, "angle": 0, "color": "Black"}}], "list": [{"id": 43, "type": "User Circle", "x": 28.4889, "y": 30.8721, "x_vel": 0, "y_vel": 0, "angle": 0.225945, "color": "Red"}, {"id": 4, "type": "circle", "x": 18.6519, "y": 29.7408, "x_vel": -2.52303, "y_vel": -1.43255, "angle": 2.01016, "color": "Green"}], "solved_state": false}, {"step": 170, "collisions": [{"kind": "begin", "1": {"id": 4, "type": "circle", "x": 18.6519, "y": 29.7408, "x_vel": -2.52303, "y_vel": -1.43255, "angle": 2.01016, "color": "Green"}, "2": {"id": 9, "type": "circle", "x": 20.159, "y": 26.9571, "x_vel": 0, "y_vel": 0, "angle": 0, "color": "Black"}}], "list": [{"id": 43, "type": "User Circle", "x": 28.4889, "y": 30.8721, "x_vel": 0, "y_vel": 0, "angle": 0.225945, "color": "Red"}, {"id": 4, "type": "circle", "x": 18.609, "y": 29.7176, "x_vel": -2.57358, "y_vel": -1.39334, "angle": 2.03358, "color": "Green"}], "solved_state": false}, {"step": 174, "collisions": [{"kind": "end", "1": {"id": 4, "type": "circle", "x": 18.4779, "y": 29.6412, "x_vel": -2.64508, "y_vel": -1.59735, "angle": 2.10642, "color": "Green"}, "2": {"id": 9, "type": "circle", "x": 20.159, "y": 26.9571, "x_vel": 0, "y_vel": 0, "angle": 0, "color": "Black"}}], "list": [{"id": 43, "type": "User Circle", "x": 28.4889, "y": 30.8721, "x_vel": 0, "y_vel": 0, "angle": 0.225945, "color": "Red"}, {"id": 4, "type": "circle", "x": 18.4338, "y": 29.6119, "x_vel": -2.64508, "y_vel": -1.76069, "angle": 2.13113, "color": "Green"}], "solved_state": false}, {"step": 175, "collisions": [{"kind": "begin", "1": {"id": 4, "type": "circle", "x": 18.4338, "y": 29.6119, "x_vel": -2.64508, "y_vel": -1.76069, "angle": 2.13113, "color": "Green"}, "2": {"id": 9, "type": "circle", "x": 20.159, "y": 26.9571, "x_vel": 0, "y_vel": 0, "angle": 0, "color": "Black"}}], "list": [{"id": 43, "type": "User Circle", "x": 28.4889, "y": 30.8721, "x_vel": 0, "y_vel": 0, "angle": 0.225945, "color": "Red"}, {"id": 4, "type": "circle", "x": 18.389, "y": 29.5827, "x_vel": -2.68911, "y_vel": -1.74748, "angle": 2.15679, "color": "Green"}], "solved_state": false}, {"step": 177, "collisions": [{"kind": "end", "1": {"id": 4, "type": "circle", "x": 18.3438, "y": 29.5523, "x_vel": -2.70939, "y_vel": -1.82645, "angle": 2.18293, "color": "Green"}, "2": {"id": 9, "type": "circle", "x": 20.159, "y": 26.9571, "x_vel": 0, "y_vel": 0, "angle": 0, "color": "Black"}}], "list": [{"id": 43, "type": "User Circle", "x": 28.4889, "y": 30.8721, "x_vel": 0, "y_vel": 0, "angle": 0.225945, "color": "Red"}, {"id": 4, "type": "circle", "x": 18.2987, "y": 29.5191, "x_vel": -2.70939, "y_vel": -1.98978, "angle": 2.20907, "color": "Green"}], "solved_state": false}, {"step": 178, "collisions": [{"kind": "begin", "1": {"id": 4, "type": "circle", "x": 18.2987, "y": 29.5191, "x_vel": -2.70939, "y_vel": -1.98978, "angle": 2.20907, "color": "Green"}, "2": {"id": 9, "type": "circle", "x": 20.159, "y": 26.9571, "x_vel": 0, "y_vel": 0, "angle": 0, "color": "Black"}}], "list": [{"id": 43, "type": "User Circle", "x": 28.4889, "y": 30.8721, "x_vel": 0, "y_vel": 0, "angle": 0.225945, "color": "Red"}, {"id": 4, "type": "circle", "x": 18.2529, "y": 29.4859, "x_vel": -2.74613, "y_vel": -1.99397, "angle": 2.23622, "color": "Green"}], "solved_state": false}, {"step": 179, "collisions": [{"kind": "end", "1": {"id": 4, "type": "circle", "x": 18.2529, "y": 29.4859, "x_vel": -2.74613, "y_vel": -1.99397, "angle": 2.23622, "color": "Green"}, "2": {"id": 9, "type": "circle", "x": 20.159, "y": 26.9571, "x_vel": 0, "y_vel": 0, "angle": 0, "color": "Black"}}], "list": [{"id": 43, "type": "User Circle", "x": 28.4889, "y": 30.8721, "x_vel": 0, "y_vel": 0, "angle": 0.225945, "color": "Red"}, {"id": 4, "type": "circle", "x": 18.2071, "y": 29.4499, "x_vel": -2.74613, "y_vel": -2.15731, "angle": 2.26337, "color": "Green"}], "solved_state": false}, {"step": 180, "collisions": [{"kind": "begin", "1": {"id": 4, "type": "circle", "x": 18.2071, "y": 29.4499, "x_vel": -2.74613, "y_vel": -2.15731, "angle": 2.26337, "color": "Green"}, "2": {"id": 9, "type": "circle", "x": 20.159, "y": 26.9571, "x_vel": 0, "y_vel": 0, "angle": 0, "color": "Black"}}], "list": [{"id": 43, "type": "User Circle", "x": 28.4889, "y": 30.8721, "x_vel": 0, "y_vel": 0, "angle": 0.225945, "color": "Red"}, {"id": 4, "type": "circle", "x": 18.1609, "y": 29.4137, "x_vel": -2.77628, "y_vel": -2.17376, "angle": 2.29159, "color": "Green"}], "solved_state": false}, {"step": 182, "collisions": [{"kind": "end", "1": {"id": 4, "type": "circle", "x": 18.1143, "y": 29.3759, "x_vel": -2.79118, "y_vel": -2.27023, "angle": 2.32028, "color": "Green"}, "2": {"id": 9, "type": "circle", "x": 20.159, "y": 26.9571, "x_vel": 0, "y_vel": 0, "angle": 0, "color": "Black"}}], "list": [{"id": 43, "type": "User Circle", "x": 28.4889, "y": 30.8721, "x_vel": 0, "y_vel": 0, "angle": 0.225945, "color": "Red"}, {"id": 4, "type": "circle", "x": 18.0678, "y": 29.3353, "x_vel": -2.79118, "y_vel": -2.43356, "angle": 2.34898, "color": "Green"}], "solved_state": false}, {"step": 184, "collisions": [{"kind": "begin", "1": {"id": 4, "type": "circle", "x": 18.0213, "y": 29.292, "x_vel": -2.79118, "y_vel": -2.5969, "angle": 2.37766, "color": "Green"}, "2": {"id": 9, "type": "circle", "x": 20.159, "y": 26.9571, "x_vel": 0, "y_vel": 0, "angle": 0, "color": "Black"}}], "list": [{"id": 43, "type": "User Circle", "x": 28.4889, "y": 30.8721, "x_vel": 0, "y_vel": 0, "angle": 0.225945, "color": "Red"}, {"id": 4, "type": "circle", "x": 17.974, "y": 29.2487, "x_vel": -2.83748, "y_vel": -2.59777, "angle": 2.40756, "color": "Green"}], "solved_state": false}, {"step": 186, "collisions": [{"kind": "end", "1": {"id": 4, "type": "circle", "x": 17.9265, "y": 29.2034, "x_vel": -2.85072, "y_vel": -2.71801, "angle": 2.43777, "color": "Green"}, "2": {"id": 9, "type": "circle", "x": 20.159, "y": 26.9571, "x_vel": 0, "y_vel": 0, "angle": 0, "color": "Black"}}], "list": [{"id": 43, "type": "User Circle", "x": 28.4889, "y": 30.8721, "x_vel": 0, "y_vel": 0, "angle": 0.225945, "color": "Red"}, {"id": 4, "type": "circle", "x": 17.879, "y": 29.1554, "x_vel": -2.85072, "y_vel": -2.88135, "angle": 2.46797, "color": "Green"}], "solved_state": false}, {"step": 189, "collisions": [{"kind": "begin", "1": {"id": 4, "type": "circle", "x": 17.784, "y": 29.0512, "x_vel": -2.85072, "y_vel": -3.20801, "angle": 2.52836, "color": "Green"}, "2": {"id": 9, "type": "circle", "x": 20.159, "y": 26.9571, "x_vel": 0, "y_vel": 0, "angle": 0, "color": "Black"}}], "list": [{"id": 43, "type": "User Circle", "x": 28.4889, "y": 30.8721, "x_vel": 0, "y_vel": 0, "angle": 0.225945, "color": "Red"}, {"id": 4, "type": "circle", "x": 17.7358, "y": 28.9966, "x_vel": -2.88905, "y_vel": -3.2766, "angle": 2.55929, "color": "Green"}], "solved_state": false}, {"step": 190, "collisions": [{"kind": "end", "1": {"id": 4, "type": "circle", "x": 17.7358, "y": 28.9966, "x_vel": -2.88905, "y_vel": -3.2766, "angle": 2.55929, "color": "Green"}, "2": {"id": 9, "type": "circle", "x": 20.159, "y": 26.9571, "x_vel": 0, "y_vel": 0, "angle": 0, "color": "Black"}}], "list": [{"id": 43, "type": "User Circle", "x": 28.4889, "y": 30.8721, "x_vel": 0, "y_vel": 0, "angle": 0.225945, "color": "Red"}, {"id": 4, "type": "circle", "x": 17.6877, "y": 28.9393, "x_vel": -2.88905, "y_vel": -3.43993, "angle": 2.5902, "color": "Green"}], "solved_state": false}, {"step": 202, "collisions": [{"kind": "begin", "1": {"id": 4, "type": "circle", "x": 17.1241, "y": 28.0655, "x_vel": -2.88905, "y_vel": -5.39994, "angle": 2.95168, "color": "Green"}, "2": {"id": 20, "type": "circle", "x": 18.0923, "y": 25.0658, "x_vel": 0, "y_vel": 0, "angle": 0, "color": "Black"}}], "list": [{"id": 43, "type": "User Circle", "x": 28.4889, "y": 30.8721, "x_vel": 0, "y_vel": 0, "angle": 0.225945, "color": "Red"}, {"id": 4, "type": "circle", "x": 17.1002, "y": 28.0716, "x_vel": -4.27928, "y_vel": -0.487713, "angle": 2.96166, "color": "Green"}], "solved_state": false}, {"step": 204, "collisions": [{"kind": "end", "1": {"id": 4, "type": "circle", "x": 17.0289, "y": 28.0608, "x_vel": -4.27928, "y_vel": -0.651046, "angle": 2.99548, "color": "Green"}, "2": {"id": 20, "type": "circle", "x": 18.0923, "y": 25.0658, "x_vel": 0, "y_vel": 0, "angle": 0, "color": "Black"}}], "list": [{"id": 43, "type": "User Circle", "x": 28.4889, "y": 30.8721, "x_vel": 0, "y_vel": 0, "angle": 0.225945, "color": "Red"}, {"id": 4, "type": "circle", "x": 16.9576, "y": 28.0472, "x_vel": -4.27928, "y_vel": -0.814379, "angle": 3.02929, "color": "Green"}], "solved_state": false}, {"step": 218, "collisions": [{"kind": "begin", "1": {"id": 4, "type": "circle", "x": 15.9697, "y": 27.5791, "x_vel": -4.27928, "y_vel": -3.10105, "angle": 3.49705, "color": "Green"}, "2": {"id": 10, "type": "circle", "x": 14.4429, "y": 24.8217, "x_vel": 0, "y_vel": 0, "angle": 0, "color": "Black"}}], "list": [{"id": 43, "type": "User Circle", "x": 28.4889, "y": 30.8721, "x_vel": 0, "y_vel": 0, "angle": 0.225945, "color": "Red"}, {"id": 4, "type": "circle", "x": 15.969, "y": 27.5927, "x_vel": -2.07255, "y_vel": 2.24178, "angle": 3.5005, "color": "Green"}], "solved_state": false}, {"step": 220, "collisions": [{"kind": "end", "1": {"id": 4, "type": "circle", "x": 15.9345, "y": 27.6273, "x_vel": -2.07255, "y_vel": 2.07844, "angle": 3.52372, "color": "Green"}, "2": {"id": 10, "type": "circle", "x": 14.4429, "y": 24.8217, "x_vel": 0, "y_vel": 0, "angle": 0, "color": "Black"}}], "list": [{"id": 43, "type": "User Circle", "x": 28.4889, "y": 30.8721, "x_vel": 0, "y_vel": 0, "angle": 0.225945, "color": "Red"}, {"id": 4, "type": "circle", "x": 15.9, "y": 27.6593, "x_vel": -2.07255, "y_vel": 1.91511, "angle": 3.54694, "color": "Green"}], "solved_state": false}, {"step": 235, "collisions": [{"kind": "begin", "1": {"id": 4, "type": "circle", "x": 15.4164, "y": 27.8203, "x_vel": -2.07255, "y_vel": -0.371555, "angle": 3.87156, "color": "Green"}, "2": {"id": 10, "type": "circle", "x": 14.4429, "y": 24.8217, "x_vel": 0, "y_vel": 0, "angle": 0, "color": "Black"}}], "list": [{"id": 43, "type": "User Circle", "x": 28.4889, "y": 30.8721, "x_vel": 0, "y_vel": 0, "angle": 0.225945, "color": "Red"}, {"id": 4, "type": "circle", "x": 15.3858, "y": 27.8432, "x_vel": -1.9905, "y_vel": 0.887777, "angle": 3.88896, "color": "Green"}], "solved_state": false}, {"step": 237, "collisions": [{"kind": "end", "1": {"id": 4, "type": "circle", "x": 15.3526, "y": 27.8552, "x_vel": -1.9905, "y_vel": 0.724444, "angle": 3.90636, "color": "Green"}, "2": {"id": 10, "type": "circle", "x": 14.4429, "y": 24.8217, "x_vel": 0, "y_vel": 0, "angle": 0, "color": "Black"}}], "list": [{"id": 43, "type": "User Circle", "x": 28.4889, "y": 30.8721, "x_vel": 0, "y_vel": 0, "angle": 0.225945, "color": "Red"}, {"id": 4, "type": "circle", "x": 15.3195, "y": 27.8646, "x_vel": -1.9905, "y_vel": 0.56111, "angle": 3.92375, "color": "Green"}], "solved_state": false}, {"step": 238, "collisions": [{"kind": "begin", "1": {"id": 4, "type": "circle", "x": 15.3195, "y": 27.8646, "x_vel": -1.9905, "y_vel": 0.56111, "angle": 3.92375, "color": "Green"}, "2": {"id": 10, "type": "circle", "x": 14.4429, "y": 24.8217, "x_vel": 0, "y_vel": 0, "angle": 0, "color": "Black"}}], "list": [{"id": 43, "type": "User Circle", "x": 28.4889, "y": 30.8721, "x_vel": 0, "y_vel": 0, "angle": 0.225945, "color": "Red"}, {"id": 4, "type": "circle", "x": 15.2863, "y": 27.8742, "x_vel": -1.99206, "y_vel": 0.573879, "angle": 3.94033, "color": "Green"}], "solved_state": false}, {"step": 239, "collisions": [{"kind": "end", "1": {"id": 4, "type": "circle", "x": 15.2863, "y": 27.8742, "x_vel": -1.99206, "y_vel": 0.573879, "angle": 3.94033, "color": "Green"}, "2": {"id": 10, "type": "circle", "x": 14.4429, "y": 24.8217, "x_vel": 0, "y_vel": 0, "angle": 0, "color": "Black"}}], "list": [{"id": 43, "type": "User Circle", "x": 28.4889, "y": 30.8721, "x_vel": 0, "y_vel": 0, "angle": 0.225945, "color": "Red"}, {"id": 4, "type": "circle", "x": 15.2531, "y": 27.881, "x_vel": -1.99206, "y_vel": 0.410545, "angle": 3.95692, "color": "Green"}], "solved_state": false}, {"step": 240, "collisions": [{"kind": "begin", "1": {"id": 4, "type": "circle", "x": 15.2531, "y": 27.881, "x_vel": -1.99206, "y_vel": 0.410545, "angle": 3.95692, "color": "Green"}, "2": {"id": 10, "type": "circle", "x": 14.4429, "y": 24.8217, "x_vel": 0, "y_vel": 0, "angle": 0, "color": "Black"}}], "list": [{"id": 43, "type": "User Circle", "x": 28.4889, "y": 30.8721, "x_vel": 0, "y_vel": 0, "angle": 0.225945, "color": "Red"}, {"id": 4, "type": "circle", "x": 15.2206, "y": 27.8896, "x_vel": -1.94928, "y_vel": 0.516232, "angle": 3.97306, "color": "Green"}], "solved_state": false}, {"step": 253, "collisions": [{"kind": "end", "1": {"id": 4, "type": "circle", "x": 14.8543, "y": 27.9616, "x_vel": -1.74727, "y_vel": 0.245493, "angle": 4.15236, "color": "Green"}, "2": {"id": 10, "type": "circle", "x": 14.4429, "y": 24.8217, "x_vel": 0, "y_vel": 0, "angle": 0, "color": "Black"}}], "list": [{"id": 43, "type": "User Circle", "x": 28.4889, "y": 30.8721, "x_vel": 0, "y_vel": 0, "angle": 0.225945, "color": "Red"}, {"id": 4, "type": "circle", "x": 14.8252, "y": 27.963, "x_vel": -1.74727, "y_vel": 0.0821594, "angle": 4.16648, "color": "Green"}], "solved_state": false}, {"step": 254, "collisions": [{"kind": "begin", "1": {"id": 4, "type": "circle", "x": 14.8252, "y": 27.963, "x_vel": -1.74727, "y_vel": 0.0821594, "angle": 4.16648, "color": "Green"}, "2": {"id": 10, "type": "circle", "x": 14.4429, "y": 24.8217, "x_vel": 0, "y_vel": 0, "angle": 0, "color": "Black"}}], "list": [{"id": 43, "type": "User Circle", "x": 28.4889, "y": 30.8721, "x_vel": 0, "y_vel": 0, "angle": 0.225945, "color": "Red"}, {"id": 4, "type": "circle", "x": 14.7965, "y": 27.9665, "x_vel": -1.7247, "y_vel": 0.209922, "angle": 4.18038, "color": "Green"}], "solved_state": false}, {"step": 273, "collisions": [{"kind": "end", "1": {"id": 4, "type": "circle", "x": 14.2955, "y": 27.9851, "x_vel": -1.66247, "y_vel": -0.0628631, "angle": 4.42132, "color": "Green"}, "2": {"id": 10, "type": "circle", "x": 14.4429, "y": 24.8217, "x_vel": 0, "y_vel": 0, "angle": 0, "color": "Black"}}], "list": [{"id": 43, "type": "User Circle", "x": 28.4889, "y": 30.8721, "x_vel": 0, "y_vel": 0, "angle": 0.225945, "color": "Red"}, {"id": 4, "type": "circle", "x": 14.2678, "y": 27.9813, "x_vel": -1.66247, "y_vel": -0.226196, "angle": 4.43463, "color": "Green"}], "solved_state": false}, {"step": 274, "collisions": [{"kind": "begin", "1": {"id": 4, "type": "circle", "x": 14.2678, "y": 27.9813, "x_vel": -1.66247, "y_vel": -0.226196, "angle": 4.43463, "color": "Green"}, "2": {"id": 10, "type": "circle", "x": 14.4429, "y": 24.8217, "x_vel": 0, "y_vel": 0, "angle": 0, "color": "Black"}}], "list": [{"id": 43, "type": "User Circle", "x": 28.4889, "y": 30.8721, "x_vel": 0, "y_vel": 0, "angle": 0.225945, "color": "Red"}, {"id": 4, "type": "circle", "x": 14.2399, "y": 27.9798, "x_vel": -1.67248, "y_vel": -0.0926717, "angle": 4.44804, "color": "Green"}], "solved_state": false}, {"step": 291, "collisions": [{"kind": "end", "1": {"id": 4, "type": "circle", "x": 13.7713, "y": 27.9165, "x_vel": -1.86378, "y_vel": -0.384945, "angle": 4.67529, "color": "Green"}, "2": {"id": 10, "type": "circle", "x": 14.4429, "y": 24.8217, "x_vel": 0, "y_vel": 0, "angle": 0, "color": "Black"}}], "list": [{"id": 43, "type": "User Circle", "x": 28.4889, "y": 30.8721, "x_vel": 0, "y_vel": 0, "angle": 0.225945, "color": "Red"}, {"id": 4, "type": "circle", "x": 13.7402, "y": 27.9073, "x_vel": -1.86378, "y_vel": -0.548279, "angle": 4.69051, "color": "Green"}], "solved_state": false}, {"step": 292, "collisions": [{"kind": "begin", "1": {"id": 4, "type": "circle", "x": 13.7402, "y": 27.9073, "x_vel": -1.86378, "y_vel": -0.548279, "angle": 4.69051, "color": "Green"}, "2": {"id": 10, "type": "circle", "x": 14.4429, "y": 24.8217, "x_vel": 0, "y_vel": 0, "angle": 0, "color": "Black"}}], "list": [{"id": 43, "type": "User Circle", "x": 28.4889, "y": 30.8721, "x_vel": 0, "y_vel": 0, "angle": 0.225945, "color": "Red"}, {"id": 4, "type": "circle", "x": 13.7085, "y": 27.9001, "x_vel": -1.90198, "y_vel": -0.433112, "angle": 4.70613, "color": "Green"}], "solved_state": false}, {"step": 303, "collisions": [{"kind": "end", "1": {"id": 4, "type": "circle", "x": 13.3716, "y": 27.8017, "x_vel": -2.12868, "y_vel": -0.736882, "angle": 4.87475, "color": "Green"}, "2": {"id": 10, "type": "circle", "x": 14.4429, "y": 24.8217, "x_vel": 0, "y_vel": 0, "angle": 0, "color": "Black"}}], "list": [{"id": 43, "type": "User Circle", "x": 28.4889, "y": 30.8721, "x_vel": 0, "y_vel": 0, "angle": 0.225945, "color": "Red"}, {"id": 4, "type": "circle", "x": 13.3361, "y": 27.7867, "x_vel": -2.12868, "y_vel": -0.900216, "angle": 4.89277, "color": "Green"}], "solved_state": false}, {"step": 304, "collisions": [{"kind": "begin", "1": {"id": 4, "type": "circle", "x": 13.3361, "y": 27.7867, "x_vel": -2.12868, "y_vel": -0.900216, "angle": 4.89277, "color": "Green"}, "2": {"id": 10, "type": "circle", "x": 14.4429, "y": 24.8217, "x_vel": 0, "y_vel": 0, "angle": 0, "color": "Black"}}], "list": [{"id": 43, "type": "User Circle", "x": 28.4889, "y": 30.8721, "x_vel": 0, "y_vel": 0, "angle": 0.225945, "color": "Red"}, {"id": 4, "type": "circle", "x": 13.2997, "y": 27.7732, "x_vel": -2.18079, "y_vel": -0.814055, "angle": 4.9114, "color": "Green"}], "solved_state": false}, {"step": 311, "collisions": [{"kind": "end", "1": {"id": 4, "type": "circle", "x": 13.0723, "y": 27.6765, "x_vel": -2.34227, "y_vel": -1.08564, "angle": 5.03009, "color": "Green"}, "2": {"id": 10, "type": "circle", "x": 14.4429, "y": 24.8217, "x_vel": 0, "y_vel": 0, "angle": 0, "color": "Black"}}], "list": [{"id": 43, "type": "User Circle", "x": 28.4889, "y": 30.8721, "x_vel": 0, "y_vel": 0, "angle": 0.225945, "color": "Red"}, {"id": 4, "type": "circle", "x": 13.0333, "y": 27.6556, "x_vel": -2.34227, "y_vel": -1.24897, "angle": 5.05074, "color": "Green"}], "solved_state": false}, {"step": 312, "collisions": [{"kind": "begin", "1": {"id": 4, "type": "circle", "x": 13.0333, "y": 27.6556, "x_vel": -2.34227, "y_vel": -1.24897, "angle": 5.05074, "color": "Green"}, "2": {"id": 10, "type": "circle", "x": 14.4429, "y": 24.8217, "x_vel": 0, "y_vel": 0, "angle": 0, "color": "Black"}}], "list": [{"id": 43, "type": "User Circle", "x": 28.4889, "y": 30.8721, "x_vel": 0, "y_vel": 0, "angle": 0.225945, "color": "Red"}, {"id": 4, "type": "circle", "x": 12.9933, "y": 27.6358, "x_vel": -2.39721, "y_vel": -1.1924, "angle": 5.07217, "color": "Green"}], "solved_state": false}, {"step": 317, "collisions": [{"kind": "end", "1": {"id": 4, "type": "circle", "x": 12.829, "y": 27.5465, "x_vel": -2.50352, "y_vel": -1.43193, "angle": 5.16194, "color": "Green"}, "2": {"id": 10, "type": "circle", "x": 14.4429, "y": 24.8217, "x_vel": 0, "y_vel": 0, "angle": 0, "color": "Black"}}], "list": [{"id": 43, "type": "User Circle", "x": 28.4889, "y": 30.8721, "x_vel": 0, "y_vel": 0, "angle": 0.225945, "color": "Red"}, {"id": 4, "type": "circle", "x": 12.7873, "y": 27.5199, "x_vel": -2.50352, "y_vel": -1.59527, "angle": 5.18501, "color": "Green"}], "solved_state": false}, {"step": 318, "collisions": [{"kind": "begin", "1": {"id": 4, "type": "circle", "x": 12.7873, "y": 27.5199, "x_vel": -2.50352, "y_vel": -1.59527, "angle": 5.18501, "color": "Green"}, "2": {"id": 10, "type": "circle", "x": 14.4429, "y": 24.8217, "x_vel": 0, "y_vel": 0, "angle": 0, "color": "Black"}}], "list": [{"id": 43, "type": "User Circle", "x": 28.4889, "y": 30.8721, "x_vel": 0, "y_vel": 0, "angle": 0.225945, "color": "Red"}, {"id": 4, "type": "circle", "x": 12.7447, "y": 27.4938, "x_vel": -2.55408, "y_vel": -1.56716, "angle": 5.20899, "color": "Green"}], "solved_state": false}, {"step": 321, "collisions": [{"kind": "end", "1": {"id": 4, "type": "circle", "x": 12.6584, "y": 27.4379, "x_vel": -2.60111, "y_vel": -1.71238, "angle": 5.25834, "color": "Green"}, "2": {"id": 10, "type": "circle", "x": 14.4429, "y": 24.8217, "x_vel": 0, "y_vel": 0, "angle": 0, "color": "Black"}}], "list": [{"id": 43, "type": "User Circle", "x": 28.4889, "y": 30.8721, "x_vel": 0, "y_vel": 0, "angle": 0.225945, "color": "Red"}, {"id": 4, "type": "circle", "x": 12.6151, "y": 27.4067, "x_vel": -2.60111, "y_vel": -1.87572, "angle": 5.28325, "color": "Green"}], "solved_state": false}, {"step": 322, "collisions": [{"kind": "begin", "1": {"id": 4, "type": "circle", "x": 12.6151, "y": 27.4067, "x_vel": -2.60111, "y_vel": -1.87572, "angle": 5.28325, "color": "Green"}, "2": {"id": 10, "type": "circle", "x": 14.4429, "y": 24.8217, "x_vel": 0, "y_vel": 0, "angle": 0, "color": "Black"}}], "list": [{"id": 43, "type": "User Circle", "x": 28.4889, "y": 30.8721, "x_vel": 0, "y_vel": 0, "angle": 0.225945, "color": "Red"}, {"id": 4, "type": "circle", "x": 12.571, "y": 27.3755, "x_vel": -2.64403, "y_vel": -1.8696, "angle": 5.30916, "color": "Green"}], "solved_state": false}, {"step": 324, "collisions": [{"kind": "end", "1": {"id": 4, "type": "circle", "x": 12.5266, "y": 27.343, "x_vel": -2.66339, "y_vel": -1.95223, "angle": 5.33558, "color": "Green"}, "2": {"id": 10, "type": "circle", "x": 14.4429, "y": 24.8217, "x_vel": 0, "y_vel": 0, "angle": 0, "color": "Black"}}], "list": [{"id": 43, "type": "User Circle", "x": 28.4889, "y": 30.8721, "x_vel": 0, "y_vel": 0, "angle": 0.225945, "color": "Red"}, {"id": 4, "type": "circle", "x": 12.4822, "y": 27.3077, "x_vel": -2.66339, "y_vel": -2.11556, "angle": 5.362, "color": "Green"}], "solved_state": false}, {"step": 325, "collisions": [{"kind": "begin", "1": {"id": 4, "type": "circle", "x": 12.4822, "y": 27.3077, "x_vel": -2.66339, "y_vel": -2.11556, "angle": 5.362, "color": "Green"}, "2": {"id": 10, "type": "circle", "x": 14.4429, "y": 24.8217, "x_vel": 0, "y_vel": 0, "angle": 0, "color": "Black"}}], "list": [{"id": 43, "type": "User Circle", "x": 28.4889, "y": 30.8721, "x_vel": 0, "y_vel": 0, "angle": 0.225945, "color": "Red"}, {"id": 4, "type": "circle", "x": 12.4373, "y": 27.2723, "x_vel": -2.69734, "y_vel": -2.12736, "angle": 5.38949, "color": "Green"}], "solved_state": false}, {"step": 327, "collisions": [{"kind": "end", "1": {"id": 4, "type": "circle", "x": 12.3921, "y": 27.2352, "x_vel": -2.71318, "y_vel": -2.22059, "angle": 5.41748, "color": "Green"}, "2": {"id": 10, "type": "circle", "x": 14.4429, "y": 24.8217, "x_vel": 0, "y_vel": 0, "angle": 0, "color": "Black"}}], "list": [{"id": 43, "type": "User Circle", "x": 28.4889, "y": 30.8721, "x_vel": 0, "y_vel": 0, "angle": 0.225945, "color": "Red"}, {"id": 4, "type": "circle", "x": 12.3468, "y": 27.1955, "x_vel": -2.71318, "y_vel": -2.38392, "angle": 5.44547, "color": "Green"}], "solved_state": false}, {"step": 329, "collisions": [{"kind": "begin", "1": {"id": 4, "type": "circle", "x": 12.3016, "y": 27.1531, "x_vel": -2.71318, "y_vel": -2.54726, "angle": 5.47346, "color": "Green"}, "2": {"id": 10, "type": "circle", "x": 14.4429, "y": 24.8217, "x_vel": 0, "y_vel": 0, "angle": 0, "color": "Black"}}], "list": [{"id": 43, "type": "User Circle", "x": 28.4889, "y": 30.8721, "x_vel": 0, "y_vel": 0, "angle": 0.225945, "color": "Red"}, {"id": 4, "type": "circle", "x": 12.2556, "y": 27.1108, "x_vel": -2.7628, "y_vel": -2.53757, "angle": 5.50273, "color": "Green"}], "solved_state": false}, {"step": 331, "collisions": [{"kind": "end", "1": {"id": 4, "type": "circle", "x": 12.2093, "y": 27.0665, "x_vel": -2.7773, "y_vel": -2.65389, "angle": 5.53235, "color": "Green"}, "2": {"id": 10, "type": "circle", "x": 14.4429, "y": 24.8217, "x_vel": 0, "y_vel": 0, "angle": 0, "color": "Black"}}], "list": [{"id": 43, "type": "User Circle", "x": 28.4889, "y": 30.8721, "x_vel": 0, "y_vel": 0, "angle": 0.225945, "color": "Red"}, {"id": 4, "type": "circle", "x": 12.163, "y": 27.0196, "x_vel": -2.7773, "y_vel": -2.81722, "angle": 5.56196, "color": "Green"}], "solved_state": false}, {"step": 333, "collisions": [{"kind": "begin", "1": {"id": 4, "type": "circle", "x": 12.1167, "y": 26.9699, "x_vel": -2.7773, "y_vel": -2.98056, "angle": 5.59156, "color": "Green"}, "2": {"id": 10, "type": "circle", "x": 14.4429, "y": 24.8217, "x_vel": 0, "y_vel": 0, "angle": 0, "color": "Black"}}], "list": [{"id": 43, "type": "User Circle", "x": 28.4889, "y": 30.8721, "x_vel": 0, "y_vel": 0, "angle": 0.225945, "color": "Red"}, {"id": 4, "type": "circle", "x": 12.0698, "y": 26.9191, "x_vel": -2.8139, "y_vel": -3.04709, "angle": 5.62191, "color": "Green"}], "solved_state": false}, {"step": 334, "collisions": [{"kind": "end", "1": {"id": 4, "type": "circle", "x": 12.0698, "y": 26.9191, "x_vel": -2.8139, "y_vel": -3.04709, "angle": 5.62191, "color": "Green"}, "2": {"id": 10, "type": "circle", "x": 14.4429, "y": 24.8217, "x_vel": 0, "y_vel": 0, "angle": 0, "color": "Black"}}], "list": [{"id": 43, "type": "User Circle", "x": 28.4889, "y": 30.8721, "x_vel": 0, "y_vel": 0, "angle": 0.225945, "color": "Red"}, {"id": 4, "type": "circle", "x": 12.0229, "y": 26.8656, "x_vel": -2.8139, "y_vel": -3.21042, "angle": 5.65224, "color": "Green"}], "solved_state": false}, {"step": 351, "collisions": [{"kind": "begin", "1": {"id": 4, "type": "circle", "x": 11.2591, "y": 25.6106, "x_vel": -2.8139, "y_vel": -5.98709, "angle": 6.14564, "color": "Green"}, "2": {"id": 11, "type": "circle", "x": 10.808, "y": 22.4914, "x_vel": 0, "y_vel": 0, "angle": 0, "color": "Black"}}], "list": [{"id": 43, "type": "User Circle", "x": 28.4889, "y": 30.8721, "x_vel": 0, "y_vel": 0, "angle": 0.225945, "color": "Red"}, {"id": 4, "type": "circle", "x": 11.2326, "y": 25.6391, "x_vel": -2.3379, "y_vel": 1.61689, "angle": 6.16017, "color": "Green"}], "solved_state": false}, {"step": 352, "collisions": [{"kind": "end", "1": {"id": 4, "type": "circle", "x": 11.2326, "y": 25.6391, "x_vel": -2.3379, "y_vel": 1.61689, "angle": 6.16017, "color": "Green"}, "2": {"id": 11, "type": "circle", "x": 10.808, "y": 22.4914, "x_vel": 0, "y_vel": 0, "angle": 0, "color": "Black"}}], "list": [{"id": 43, "type": "User Circle", "x": 28.4889, "y": 30.8721, "x_vel": 0, "y_vel": 0, "angle": 0.225945, "color": "Red"}, {"id": 4, "type": "circle", "x": 11.1937, "y": 25.6633, "x_vel": -2.3379, "y_vel": 1.45355, "angle": 6.18056, "color": "Green"}], "solved_state": false}, {"step": 371, "collisions": [{"kind": "begin", "1": {"id": 4, "type": "circle", "x": 10.4923, "y": 25.6339, "x_vel": -2.3379, "y_vel": -1.48645, "angle": 6.54693, "color": "Green"}, "2": {"id": 11, "type": "circle", "x": 10.808, "y": 22.4914, "x_vel": 0, "y_vel": 0, "angle": 0, "color": "Black"}}], "list": [{"id": 43, "type": "User Circle", "x": 28.4889, "y": 30.8721, "x_vel": 0, "y_vel": 0, "angle": 0.225945, "color": "Red"}, {"id": 4, "type": "circle", "x": 10.4503, "y": 25.6344, "x_vel": -2.5214, "y_vel": 0.0296792, "angle": 6.56701, "color": "Green"}], "solved_state": false}, {"step": 374, "collisions": [{"kind": "end", "1": {"id": 4, "type": "circle", "x": 10.3662, "y": 25.6272, "x_vel": -2.5214, "y_vel": -0.296988, "angle": 6.60718, "color": "Green"}, "2": {"id": 11, "type": "circle", "x": 10.808, "y": 22.4914, "x_vel": 0, "y_vel": 0, "angle": 0, "color": "Black"}}], "list": [{"id": 43, "type": "User Circle", "x": 28.4889, "y": 30.8721, "x_vel": 0, "y_vel": 0, "angle": 0.225945, "color": "Red"}, {"id": 4, "type": "circle", "x": 10.3242, "y": 25.6195, "x_vel": -2.5214, "y_vel": -0.460321, "angle": 6.62725, "color": "Green"}], "solved_state": false}, {"step": 375, "collisions": [{"kind": "begin", "1": {"id": 4, "type": "circle", "x": 10.3242, "y": 25.6195, "x_vel": -2.5214, "y_vel": -0.460321, "angle": 6.62725, "color": "Green"}, "2": {"id": 11, "type": "circle", "x": 10.808, "y": 22.4914, "x_vel": 0, "y_vel": 0, "angle": 0, "color": "Black"}}], "list": [{"id": 43, "type": "User Circle", "x": 28.4889, "y": 30.8721, "x_vel": 0, "y_vel": 0, "angle": 0.225945, "color": "Red"}, {"id": 4, "type": "circle", "x": 10.282, "y": 25.613, "x_vel": -2.53076, "y_vel": -0.391402, "angle": 6.64775, "color": "Green"}], "solved_state": false}, {"step": 380, "collisions": [{"kind": "end", "1": {"id": 4, "type": "circle", "x": 10.1112, "y": 25.5806, "x_vel": -2.58409, "y_vel": -0.545275, "angle": 6.73125, "color": "Green"}, "2": {"id": 11, "type": "circle", "x": 10.808, "y": 22.4914, "x_vel": 0, "y_vel": 0, "angle": 0, "color": "Black"}}], "list": [{"id": 43, "type": "User Circle", "x": 28.4889, "y": 30.8721, "x_vel": 0, "y_vel": 0, "angle": 0.225945, "color": "Red"}, {"id": 4, "type": "circle", "x": 10.0681, "y": 25.5688, "x_vel": -2.58409, "y_vel": -0.708608, "angle": 6.75238, "color": "Green"}], "solved_state": false}, {"step": 381, "collisions": [{"kind": "begin", "1": {"id": 4, "type": "circle", "x": 10.0681, "y": 25.5688, "x_vel": -2.58409, "y_vel": -0.708608, "angle": 6.75238, "color": "Green"}, "2": {"id": 11, "type": "circle", "x": 10.808, "y": 22.4914, "x_vel": 0, "y_vel": 0, "angle": 0, "color": "Black"}}], "list": [{"id": 43, "type": "User Circle", "x": 28.4889, "y": 30.8721, "x_vel": 0, "y_vel": 0, "angle": 0.225945, "color": "Red"}, {"id": 4, "type": "circle", "x": 10.0245, "y": 25.5583, "x_vel": -2.61606, "y_vel": -0.628992, "angle": 6.77391, "color": "Green"}], "solved_state": false}, {"step": 386, "collisions": [{"kind": "end", "1": {"id": 4, "type": "circle", "x": 9.8472, "y": 25.5089, "x_vel": -2.68641, "y_vel": -0.811881, "angle": 6.86228, "color": "Green"}, "2": {"id": 11, "type": "circle", "x": 10.808, "y": 22.4914, "x_vel": 0, "y_vel": 0, "angle": 0, "color": "Black"}}], "list": [{"id": 43, "type": "User Circle", "x": 28.4889, "y": 30.8721, "x_vel": 0, "y_vel": 0, "angle": 0.225945, "color": "Red"}, {"id": 4, "type": "circle", "x": 9.80243, "y": 25.4926, "x_vel": -2.68641, "y_vel": -0.975215, "angle": 6.88473, "color": "Green"}], "solved_state": false}, {"step": 387, "collisions": [{"kind": "begin", "1": {"id": 4, "type": "circle", "x": 9.80243, "y": 25.4926, "x_vel": -2.68641, "y_vel": -0.975215, "angle": 6.88473, "color": "Green"}, "2": {"id": 11, "type": "circle", "x": 10.808, "y": 22.4914, "x_vel": 0, "y_vel": 0, "angle": 0, "color": "Black"}}], "list": [{"id": 43, "type": "User Circle", "x": 28.4889, "y": 30.8721, "x_vel": 0, "y_vel": 0, "angle": 0.225945, "color": "Red"}, {"id": 4, "type": "circle", "x": 9.75701, "y": 25.4774, "x_vel": -2.72526, "y_vel": -0.913113, "angle": 6.90773, "color": "Green"}], "solved_state": false}, {"step": 391, "collisions": [{"kind": "end", "1": {"id": 4, "type": "circle", "x": 9.61876, "y": 25.4263, "x_vel": -2.78511, "y_vel": -1.07789, "angle": 6.97849, "color": "Green"}, "2": {"id": 11, "type": "circle", "x": 10.808, "y": 22.4914, "x_vel": 0, "y_vel": 0, "angle": 0, "color": "Black"}}], "list": [{"id": 43, "type": "User Circle", "x": 28.4889, "y": 30.8721, "x_vel": 0, "y_vel": 0, "angle": 0.225945, "color": "Red"}, {"id": 4, "type": "circle", "x": 9.57234, "y": 25.4056, "x_vel": -2.78511, "y_vel": -1.24123, "angle": 7.00238, "color": "Green"}], "solved_state": false}, {"step": 392, "collisions": [{"kind": "begin", "1": {"id": 4, "type": "circle", "x": 9.57234, "y": 25.4056, "x_vel": -2.78511, "y_vel": -1.24123, "angle": 7.00238, "color": "Green"}, "2": {"id": 11, "type": "circle", "x": 10.808, "y": 22.4914, "x_vel": 0, "y_vel": 0, "angle": 0, "color": "Black"}}], "list": [{"id": 43, "type": "User Circle", "x": 28.4889, "y": 30.8721, "x_vel": 0, "y_vel": 0, "angle": 0.225945, "color": "Red"}, {"id": 4, "type": "circle", "x": 9.52523, "y": 25.3856, "x_vel": -2.82629, "y_vel": -1.19837, "angle": 7.02695, "color": "Green"}], "solved_state": false}, {"step": 396, "collisions": [{"kind": "end", "1": {"id": 4, "type": "circle", "x": 9.3819, "y": 25.3192, "x_vel": -2.88659, "y_vel": -1.39514, "angle": 7.10279, "color": "Green"}, "2": {"id": 11, "type": "circle", "x": 10.808, "y": 22.4914, "x_vel": 0, "y_vel": 0, "angle": 0, "color": "Black"}}], "list": [{"id": 43, "type": "User Circle", "x": 28.4889, "y": 30.8721, "x_vel": 0, "y_vel": 0, "angle": 0.225945, "color": "Red"}, {"id": 4, "type": "circle", "x": 9.33379, "y": 25.2933, "x_vel": -2.88659, "y_vel": -1.55847, "angle": 7.12843, "color": "Green"}], "solved_state": false}, {"step": 397, "collisions": [{"kind": "begin", "1": {"id": 4, "type": "circle", "x": 9.33379, "y": 25.2933, "x_vel": -2.88659, "y_vel": -1.55847, "angle": 7.12843, "color": "Green"}, "2": {"id": 11, "type": "circle", "x": 10.808, "y": 22.4914, "x_vel": 0, "y_vel": 0, "angle": 0, "color": "Black"}}], "list": [{"id": 43, "type": "User Circle", "x": 28.4889, "y": 30.8721, "x_vel": 0, "y_vel": 0, "angle": 0.225945, "color": "Red"}, {"id": 4, "type": "circle", "x": 9.28504, "y": 25.2676, "x_vel": -2.92547, "y_vel": -1.53923, "angle": 7.15488, "color": "Green"}], "solved_state": false}, {"step": 399, "collisions": [{"kind": "end", "1": {"id": 4, "type": "circle", "x": 9.23597, "y": 25.2407, "x_vel": -2.94382, "y_vel": -1.6149, "angle": 7.18175, "color": "Green"}, "2": {"id": 11, "type": "circle", "x": 10.808, "y": 22.4914, "x_vel": 0, "y_vel": 0, "angle": 0, "color": "Black"}}], "list": [{"id": 43, "type": "User Circle", "x": 28.4889, "y": 30.8721, "x_vel": 0, "y_vel": 0, "angle": 0.225945, "color": "Red"}, {"id": 4, "type": "circle", "x": 9.18691, "y": 25.2111, "x_vel": -2.94382, "y_vel": -1.77823, "angle": 7.2086, "color": "Green"}], "solved_state": false}, {"step": 400, "collisions": [{"kind": "begin", "1": {"id": 4, "type": "circle", "x": 9.18691, "y": 25.2111, "x_vel": -2.94382, "y_vel": -1.77823, "angle": 7.2086, "color": "Green"}, "2": {"id": 11, "type": "circle", "x": 10.808, "y": 22.4914, "x_vel": 0, "y_vel": 0, "angle": 0, "color": "Black"}}], "list": [{"id": 43, "type": "User Circle", "x": 28.4889, "y": 30.8721, "x_vel": 0, "y_vel": 0, "angle": 0.225945, "color": "Red"}, {"id": 4, "type": "circle", "x": 9.13727, "y": 25.1815, "x_vel": -2.97832, "y_vel": -1.77526, "angle": 7.23634, "color": "Green"}], "solved_state": false}, {"step": 401, "collisions": [{"kind": "end", "1": {"id": 4, "type": "circle", "x": 9.13727, "y": 25.1815, "x_vel": -2.97832, "y_vel": -1.77526, "angle": 7.23634, "color": "Green"}, "2": {"id": 11, "type": "circle", "x": 10.808, "y": 22.4914, "x_vel": 0, "y_vel": 0, "angle": 0, "color": "Black"}}], "list": [{"id": 43, "type": "User Circle", "x": 28.4889, "y": 30.8721, "x_vel": 0, "y_vel": 0, "angle": 0.225945, "color": "Red"}, {"id": 4, "type": "circle", "x": 9.08763, "y": 25.1492, "x_vel": -2.97832, "y_vel": -1.93859, "angle": 7.26408, "color": "Green"}], "solved_state": false}, {"step": 402, "collisions": [{"kind": "begin", "1": {"id": 4, "type": "circle", "x": 9.08763, "y": 25.1492, "x_vel": -2.97832, "y_vel": -1.93859, "angle": 7.26408, "color": "Green"}, "2": {"id": 11, "type": "circle", "x": 10.808, "y": 22.4914, "x_vel": 0, "y_vel": 0, "angle": 0, "color": "Black"}}], "list": [{"id": 43, "type": "User Circle", "x": 28.4889, "y": 30.8721, "x_vel": 0, "y_vel": 0, "angle": 0.225945, "color": "Red"}, {"id": 4, "type": "circle", "x": 9.03749, "y": 25.1167, "x_vel": -3.00834, "y_vel": -1.94729, "angle": 7.29275, "color": "Green"}], "solved_state": false}, {"step": 404, "collisions": [{"kind": "end", "1": {"id": 4, "type": "circle", "x": 8.98714, "y": 25.0828, "x_vel": -3.02117, "y_vel": -2.03747, "angle": 7.32191, "color": "Green"}, "2": {"id": 11, "type": "circle", "x": 10.808, "y": 22.4914, "x_vel": 0, "y_vel": 0, "angle": 0, "color": "Black"}}], "list": [{"id": 43, "type": "User Circle", "x": 28.4889, "y": 30.8721, "x_vel": 0, "y_vel": 0, "angle": 0.225945, "color": "Red"}, {"id": 4, "type": "circle", "x": 8.93678, "y": 25.0461, "x_vel": -3.02117, "y_vel": -2.2008, "angle": 7.35106, "color": "Green"}], "solved_state": false}, {"step": 406, "collisions": [{"kind": "begin", "1": {"id": 4, "type": "circle", "x": 8.88643, "y": 25.0067, "x_vel": -3.02117, "y_vel": -2.36413, "angle": 7.3802, "color": "Green"}, "2": {"id": 11, "type": "circle", "x": 10.808, "y": 22.4914, "x_vel": 0, "y_vel": 0, "angle": 0, "color": "Black"}}], "list": [{"id": 43, "type": "User Circle", "x": 28.4889, "y": 30.8721, "x_vel": 0, "y_vel": 0, "angle": 0.225945, "color": "Red"}, {"id": 4, "type": "circle", "x": 8.83547, "y": 24.9677, "x_vel": -3.05774, "y_vel": -2.33598, "angle": 7.41073, "color": "Green"}], "solved_state": false}, {"step": 409, "collisions": [{"kind": "end", "1": {"id": 4, "type": "circle", "x": 8.73297, "y": 24.8843, "x_vel": -3.08064, "y_vel": -2.55963, "angle": 7.47294, "color": "Green"}, "2": {"id": 11, "type": "circle", "x": 10.808, "y": 22.4914, "x_vel": 0, "y_vel": 0, "angle": 0, "color": "Black"}}], "list": [{"id": 43, "type": "User Circle", "x": 28.4889, "y": 30.8721, "x_vel": 0, "y_vel": 0, "angle": 0.225945, "color": "Red"}, {"id": 4, "type": "circle", "x": 8.68163, "y": 24.8389, "x_vel": -3.08064, "y_vel": -2.72297, "angle": 7.50421, "color": "Green"}], "solved_state": false}, {"step": 412, "collisions": [{"kind": "begin", "1": {"id": 4, "type": "circle", "x": 8.57894, "y": 24.74, "x_vel": -3.08064, "y_vel": -3.04963, "angle": 7.56674, "color": "Green"}, "2": {"id": 11, "type": "circle", "x": 10.808, "y": 22.4914, "x_vel": 0, "y_vel": 0, "angle": 0, "color": "Black"}}], "list": [{"id": 43, "type": "User Circle", "x": 28.4889, "y": 30.8721, "x_vel": 0, "y_vel": 0, "angle": 0.225945, "color": "Red"}, {"id": 4, "type": "circle", "x": 8.52694, "y": 24.6885, "x_vel": -3.12008, "y_vel": -3.09293, "angle": 7.5989, "color": "Green"}], "solved_state": false}, {"step": 413, "collisions": [{"kind": "end", "1": {"id": 4, "type": "circle", "x": 8.52694, "y": 24.6885, "x_vel": -3.12008, "y_vel": -3.09293, "angle": 7.5989, "color": "Green"}, "2": {"id": 11, "type": "circle", "x": 10.808, "y": 22.4914, "x_vel": 0, "y_vel": 0, "angle": 0, "color": "Black"}}], "list": [{"id": 43, "type": "User Circle", "x": 28.4889, "y": 30.8721, "x_vel": 0, "y_vel": 0, "angle": 0.225945, "color": "Red"}, {"id": 4, "type": "circle", "x": 8.47494, "y": 24.6342, "x_vel": -3.12008, "y_vel": -3.25626, "angle": 7.63105, "color": "Green"}], "solved_state": false}, {"step": 416, "collisions": [{"kind": "begin", "1": {"id": 4, "type": "circle", "x": 8.33904, "y": 24.4792, "x_vel": -3.12008, "y_vel": -3.74626, "angle": 7.71506, "color": "Green"}, "2": {"id": 21, "type": "circle", "x": 8.53333, "y": 21.3333, "x_vel": 0, "y_vel": 0, "angle": 0, "color": "Black"}}], "list": [{"id": 43, "type": "User Circle", "x": 28.4889, "y": 30.8721, "x_vel": 0, "y_vel": 0, "angle": 0.225945, "color": "Red"}, {"id": 4, "type": "circle", "x": 8.31524, "y": 24.4915, "x_vel": -3.60473, "y_vel": 0.488074, "angle": 7.72611, "color": "Green"}], "solved_state": false}, {"step": 418, "collisions": [{"kind": "end", "1": {"id": 4, "type": "circle", "x": 8.25516, "y": 24.4969, "x_vel": -3.60473, "y_vel": 0.324741, "angle": 7.75469, "color": "Green"}, "2": {"id": 21, "type": "circle", "x": 8.53333, "y": 21.3333, "x_vel": 0, "y_vel": 0, "angle": 0, "color": "Black"}}], "list": [{"id": 43, "type": "User Circle", "x": 28.4889, "y": 30.8721, "x_vel": 0, "y_vel": 0, "angle": 0.225945, "color": "Red"}, {"id": 4, "type": "circle", "x": 8.19509, "y": 24.4996, "x_vel": -3.60473, "y_vel": 0.161408, "angle": 7.78326, "color": "Green"}], "solved_state": false}, {"step": 432, "collisions": [{"kind": "begin", "1": {"id": 4, "type": "circle", "x": 7.41406, "y": 24.2869, "x_vel": -3.60473, "y_vel": -1.96193, "angle": 8.15425, "color": "Green"}, "2": {"id": 21, "type": "circle", "x": 8.53333, "y": 21.3333, "x_vel": 0, "y_vel": 0, "angle": 0, "color": "Black"}}], "list": [{"id": 43, "type": "User Circle", "x": 28.4889, "y": 30.8721, "x_vel": 0, "y_vel": 0, "angle": 0.225945, "color": "Red"}, {"id": 4, "type": "circle", "x": 7.35256, "y": 24.2641, "x_vel": -3.67885, "y_vel": -1.39414, "angle": 8.18578, "color": "Green"}], "solved_state": false}, {"step": 442, "collisions": [{"kind": "end", "1": {"id": 4, "type": "circle", "x": 6.79649, "y": 23.9814, "x_vel": -3.72175, "y_vel": -2.31999, "angle": 8.4854, "color": "Green"}, "2": {"id": 21, "type": "circle", "x": 8.53333, "y": 21.3333, "x_vel": 0, "y_vel": 0, "angle": 0, "color": "Black"}}], "list": [{"id": 43, "type": "User Circle", "x": 28.4889, "y": 30.8721, "x_vel": 0, "y_vel": 0, "angle": 0.225945, "color": "Red"}, {"id": 4, "type": "circle", "x": 6.73446, "y": 23.94, "x_vel": -3.72175, "y_vel": -2.48332, "angle": 8.52013, "color": "Green"}], "solved_state": false}, {"step": 445, "collisions": [{"kind": "begin", "1": {"id": 4, "type": "circle", "x": 6.6104, "y": 23.8491, "x_vel": -3.72175, "y_vel": -2.80999, "angle": 8.58957, "color": "Green"}, "2": {"id": 21, "type": "circle", "x": 8.53333, "y": 21.3333, "x_vel": 0, "y_vel": 0, "angle": 0, "color": "Black"}}], "list": [{"id": 43, "type": "User Circle", "x": 28.4889, "y": 30.8721, "x_vel": 0, "y_vel": 0, "angle": 0.225945, "color": "Red"}, {"id": 4, "type": "circle", "x": 6.54801, "y": 23.8014, "x_vel": -3.7432, "y_vel": -2.86114, "angle": 8.6251, "color": "Green"}], "solved_state": false}, {"step": 446, "collisions": [{"kind": "end", "1": {"id": 4, "type": "circle", "x": 6.54801, "y": 23.8014, "x_vel": -3.7432, "y_vel": -2.86114, "angle": 8.6251, "color": "Green"}, "2": {"id": 21, "type": "circle", "x": 8.53333, "y": 21.3333, "x_vel": 0, "y_vel": 0, "angle": 0, "color": "Black"}}], "list": [{"id": 43, "type": "User Circle", "x": 28.4889, "y": 30.8721, "x_vel": 0, "y_vel": 0, "angle": 0.225945, "color": "Red"}, {"id": 4, "type": "circle", "x": 6.48563, "y": 23.751, "x_vel": -3.7432, "y_vel": -3.02447, "angle": 8.66062, "color": "Green"}], "solved_state": false}, {"step": 481, "collisions": [{"kind": "begin", "1": {"id": 4, "type": "circle", "x": 4.31815, "y": 20.3092, "x_vel": -3.7432, "y_vel": -8.74114, "angle": 9.89108, "color": "Green"}, "2": {"id": 22, "type": "circle", "x": 6.55229, "y": 18.0862, "x_vel": 0, "y_vel": 0, "angle": 0, "color": "Black"}}], "list": [{"id": 43, "type": "User Circle", "x": 28.4889, "y": 30.8721, "x_vel": 0, "y_vel": 0, "angle": 0.225945, "color": "Red"}, {"id": 4, "type": "circle", "x": 4.28711, "y": 20.2956, "x_vel": -5.68768, "y_vel": -4.7204, "angle": 9.90625, "color": "Green"}], "solved_state": false}, {"step": 483, "collisions": [{"kind": "end", "1": {"id": 4, "type": "circle", "x": 4.19232, "y": 20.2142, "x_vel": -5.68768, "y_vel": -4.88374, "angle": 9.96519, "color": "Green"}, "2": {"id": 22, "type": "circle", "x": 6.55229, "y": 18.0862, "x_vel": 0, "y_vel": 0, "angle": 0, "color": "Black"}}], "list": [{"id": 43, "type": "User Circle", "x": 28.4889, "y": 30.8721, "x_vel": 0, "y_vel": 0, "angle": 0.225945, "color": "Red"}, {"id": 4, "type": "circle", "x": 4.09752, "y": 20.1301, "x_vel": -5.68768, "y_vel": -5.04707, "angle": 10.0241, "color": "Green"}], "solved_state": false}, {"step": 505, "collisions": [{"kind": "begin", "1": {"id": 1, "type": "boundary", "x": -0.416667, "y": 21.3333, "x_vel": 0, "y_vel": 0, "angle": 0, "color": "Black"}, "2": {"id": 4, "type": "circle", "x": 2.07833, "y": 17.6915, "x_vel": -5.68768, "y_vel": -8.6404, "angle": 11.2769, "color": "Green"}}], "list": [{"id": 43, "type": "User Circle", "x": 28.4889, "y": 30.8721, "x_vel": 0, "y_vel": 0, "angle": 0.225945, "color": "Red"}, {"id": 4, "type": "circle", "x": 2.10097, "y": 17.6305, "x_vel": 1.13754, "y_vel": -5.22779, "angle": 11.2798, "color": "Green"}], "solved_state": false}, {"step": 506, "collisions": [{"kind": "end", "1": {"id": 1, "type": "boundary", "x": -0.416667, "y": 21.3333, "x_vel": 0, "y_vel": 0, "angle": 0, "color": "Black"}, "2": {"id": 4, "type": "circle", "x": 2.10097, "y": 17.6305, "x_vel": 1.13754, "y_vel": -5.22779, "angle": 11.2798, "color": "Green"}}], "list": [{"id": 43, "type": "User Circle", "x": 28.4889, "y": 30.8721, "x_vel": 0, "y_vel": 0, "angle": 0.225945, "color": "Red"}, {"id": 4, "type": "circle", "x": 2.11993, "y": 17.5407, "x_vel": 1.13754, "y_vel": -5.39113, "angle": 11.284, "color": "Green"}], "solved_state": false}, {"step": 582, "collisions": [{"kind": "begin", "1": {"id": 42, "type": "bar", "x": 21.3333, "y": 0.426667, "x_vel": 0, "y_vel": 0, "angle": 0, "color": "Purple"}, "2": {"id": 4, "type": "circle", "x": 3.549, "y": 2.93167, "x_vel": 1.13754, "y_vel": -17.8044, "angle": 11.597, "color": "Green"}}], "list": [{"id": 43, "type": "User Circle", "x": 28.4889, "y": 30.8721, "x_vel": 0, "y_vel": 0, "angle": 0.225945, "color": "Red"}, {"id": 4, "type": "circle", "x": 3.55508, "y": 2.97803, "x_vel": 0.585677, "y_vel": 3.56089, "angle": 11.594, "color": "Green"}], "solved_state": true}, {"step": 583, "collisions": [{"kind": "end", "1": {"id": 42, "type": "bar", "x": 21.3333, "y": 0.426667, "x_vel": 0, "y_vel": 0, "angle": 0, "color": "Purple"}, "2": {"id": 4, "type": "circle", "x": 3.55508, "y": 2.97803, "x_vel": 0.585677, "y_vel": 3.56089, "angle": 11.594, "color": "Green"}}], "list": [{"id": 43, "type": "User Circle", "x": 28.4889, "y": 30.8721, "x_vel": 0, "y_vel": 0, "angle": 0.225945, "color": "Red"}, {"id": 4, "type": "circle", "x": 3.56484, "y": 3.03466, "x_vel": 0.585677, "y_vel": 3.39756, "angle": 11.5893, "color": "Green"}], "solved_state": false}, {"step": 626, "collisions": [{"kind": "begin", "1": {"id": 42, "type": "bar", "x": 21.3333, "y": 0.426667, "x_vel": 0, "y_vel": 0, "angle": 0, "color": "Purple"}, "2": {"id": 4, "type": "circle", "x": 3.97855, "y": 2.93167, "x_vel": 0.585677, "y_vel": -3.62578, "angle": 11.3912, "color": "Green"}}], "list": [{"id": 43, "type": "User Circle", "x": 28.4889, "y": 30.8721, "x_vel": 0, "y_vel": 0, "angle": 0.225945, "color": "Red"}, {"id": 4, "type": "circle", "x": 3.98456, "y": 2.9485, "x_vel": 0.584248, "y_vel": 0.725156, "angle": 11.3884, "color": "Green"}], "solved_state": true}, {"step": 627, "collisions": [{"kind": "end", "1": {"id": 42, "type": "bar", "x": 21.3333, "y": 0.426667, "x_vel": 0, "y_vel": 0, "angle": 0, "color": "Purple"}, "2": {"id": 4, "type": "circle", "x": 3.98456, "y": 2.9485, "x_vel": 0.584248, "y_vel": 0.725156, "angle": 11.3884, "color": "Green"}}], "list": [{"id": 43, "type": "User Circle", "x": 28.4889, "y": 30.8721, "x_vel": 0, "y_vel": 0, "angle": 0.225945, "color": "Red"}, {"id": 4, "type": "circle", "x": 3.9943, "y": 2.95787, "x_vel": 0.584248, "y_vel": 0.561822, "angle": 11.3837, "color": "Green"}], "solved_state": false}, {"step": 636, "collisions": [{"kind": "begin", "1": {"id": 42, "type": "bar", "x": 21.3333, "y": 0.426667, "x_vel": 0, "y_vel": 0, "angle": 0, "color": "Purple"}, "2": {"id": 4, "type": "circle", "x": 4.0722, "y": 2.93478, "x_vel": 0.584248, "y_vel": -0.744844, "angle": 11.3463, "color": "Green"}}], "list": [{"id": 43, "type": "User Circle", "x": 28.4889, "y": 30.8721, "x_vel": 0, "y_vel": 0, "angle": 0.225945, "color": "Red"}, {"id": 4, "type": "circle", "x": 4.08193, "y": 2.93616, "x_vel": 0.583628, "y_vel": 0, "angle": 11.3416, "color": "Green"}], "solved_state": true}, {"step": 698, "collisions": [{"kind": "begin", "1": {"id": 4, "type": "circle", "x": 4.67457, "y": 2.94167, "x_vel": 0.581972, "y_vel": 0, "angle": 11.0567, "color": "Green"}, "2": {"id": 30, "type": "circle", "x": 6.78318, "y": 5.30239, "x_vel": 0, "y_vel": 0, "angle": 0, "color": "Black"}}], "list": [{"id": 43, "type": "User Circle", "x": 28.4889, "y": 30.8721, "x_vel": 0, "y_vel": 0, "angle": 0.225945, "color": "Red"}, {"id": 4, "type": "circle", "x": 4.67457, "y": 2.94167, "x_vel": 5.10462e-09, "y_vel": -6.8623e-09, "angle": 11.0567, "color": "Green"}], "solved_state": true}]